imdata/__init__.py
imdata-0.0.4.dist-info/METADATA
imdata-0.0.4.dist-info/WHEEL
imdata-0.0.4.dist-info/top_level.txt
imdata-0.0.4.dist-info/RECORD
