Metadata-Version: 2.1
Name: imdata
Version: 0.0.4
Summary: A easy class for save the data in an image
Home-page: https://github.com/jeefies/imdata
Author: Jeefy
Author-email: Jeefy <jeefy163@163.com>
Project-URL: Homepage, https://github.com/jeefies/imdata
Project-URL: Bug Tracker, https://github.com/jeefies/imdata/issues
Classifier: Programming Language :: Python :: 3
Requires-Python: >3.4
Requires-Dist: numpy
Requires-Dist: imageio
